[
  {
    "title": "Sac County Board of Supervisors Meeting",
    "description": "Sign up to take notes for this meeting at https://www.socialjusticesac.org/wix-sac-bos",
    "url": "http://saccounty.mhsoftware.com/ViewItem.html?integral=0&cal_item_id=4567&dtwhen=2460501",
    "uid": "58d19d703a71dc087a0c623734b2a541-2bc412c3:18b7816708b:afa",
    "start": [
      2024,
      7,
      9,
      16,
      30
    ],
    "duration": {
      "hours": 2
    },
    "startInputType": "utc"
  },
  {
    "title": "Sac County Board of Supervisors Meeting",
    "description": "Sign up to take notes for this meeting at https://www.socialjusticesac.org/wix-sac-bos",
    "url": "http://saccounty.mhsoftware.com/ViewItem.html?integral=0&cal_item_id=4568&dtwhen=2460515",
    "uid": "58d19d703a71dc087a0c623734b2a541-2bc412c3:18b7816708b:afb",
    "start": [
      2024,
      7,
      23,
      16,
      30
    ],
    "duration": {
      "hours": 2
    },
    "startInputType": "utc"
  },
  {
    "title": "Sac County Board of Supervisors Meeting",
    "description": "Sign up to take notes for this meeting at https://www.socialjusticesac.org/wix-sac-bos",
    "url": "http://saccounty.mhsoftware.com/ViewItem.html?integral=0&cal_item_id=4602&dtwhen=2460516",
    "uid": "58d19d703a71dc087a0c623734b2a541-2bc412c3:18b7816708b:b25",
    "start": [
      2024,
      7,
      24,
      21,
      0
    ],
    "duration": {
      "hours": 2
    },
    "startInputType": "utc"
  },
  {
    "title": "Sac County Board of Supervisors Meeting",
    "description": "Sign up to take notes for this meeting at https://www.socialjusticesac.org/wix-sac-bos",
    "url": "http://saccounty.mhsoftware.com/ViewItem.html?integral=0&cal_item_id=4569&dtwhen=2460529",
    "uid": "58d19d703a71dc087a0c623734b2a541-2bc412c3:18b7816708b:afe",
    "start": [
      2024,
      8,
      6,
      16,
      30
    ],
    "duration": {
      "hours": 2
    },
    "startInputType": "utc"
  },
  {
    "title": "Sacramento City Council",
    "description": "Sign up to take notes for this meeting at https://www.socialjusticesac.org/wix-sac-city-council",
    "url": "",
    "start": [
      2021,
      1,
      6,
      1,
      0
    ],
    "duration": {
      "hours": 2
    },
    "startInputType": "utc",
    "uid": "cd9ac536-e183-45ea-988a-10db47f53029"
  },
  {
    "title": "Sacramento City Council",
    "description": "Sign up to take notes for this meeting at https://www.socialjusticesac.org/wix-sac-city-council",
    "url": "",
    "start": [
      2021,
      1,
      12,
      22,
      0
    ],
    "duration": {
      "hours": 2
    },
    "startInputType": "utc",
    "uid": "871a9a39-58ea-4af9-8d1b-9dcd40af8b8f"
  },
  {
    "title": "Sacramento City Council",
    "description": "Sign up to take notes for this meeting at https://www.socialjusticesac.org/wix-sac-city-council",
    "url": "",
    "start": [
      2021,
      1,
      19,
      22,
      0
    ],
    "duration": {
      "hours": 2
    },
    "startInputType": "utc",
    "uid": "60980a14-682f-4657-8916-06217aef41cf"
  },
  {
    "title": "Sacramento City Council",
    "description": "Sign up to take notes for this meeting at https://www.socialjusticesac.org/wix-sac-city-council",
    "url": "",
    "start": [
      2021,
      1,
      20,
      1,
      0
    ],
    "duration": {
      "hours": 2
    },
    "startInputType": "utc",
    "uid": "9aab06d9-486c-4ca7-9d1b-4af41b4531e2"
  },
  {
    "title": "Sacramento City Council",
    "description": "Sign up to take notes for this meeting at https://www.socialjusticesac.org/wix-sac-city-council",
    "url": "",
    "start": [
      2021,
      1,
      27,
      1,
      0
    ],
    "duration": {
      "hours": 2
    },
    "startInputType": "utc",
    "uid": "6a85feb9-ba29-4680-98a9-b8b522e6214f"
  },
  {
    "title": "Sacramento City Council",
    "description": "Sign up to take notes for this meeting at https://www.socialjusticesac.org/wix-sac-city-council",
    "url": "",
    "start": [
      2021,
      2,
      3,
      1,
      0
    ],
    "duration": {
      "hours": 2
    },
    "startInputType": "utc",
    "uid": "074d72f4-4209-4f6e-9e53-14c63d4a33bb"
  },
  {
    "title": "Sacramento City Council",
    "description": "Sign up to take notes for this meeting at https://www.socialjusticesac.org/wix-sac-city-council",
    "url": "",
    "start": [
      2021,
      2,
      9,
      22,
      0
    ],
    "duration": {
      "hours": 2
    },
    "startInputType": "utc",
    "uid": "0c3426cd-3922-43cd-9f87-620ca4207c4a"
  },
  {
    "title": "Sacramento City Council",
    "description": "Sign up to take notes for this meeting at https://www.socialjusticesac.org/wix-sac-city-council",
    "url": "",
    "start": [
      2021,
      2,
      17,
      1,
      0
    ],
    "duration": {
      "hours": 2
    },
    "startInputType": "utc",
    "uid": "a7571f47-bb11-4494-bf55-f46e0b95e5be"
  },
  {
    "title": "Sacramento City Council",
    "description": "Sign up to take notes for this meeting at https://www.socialjusticesac.org/wix-sac-city-council",
    "url": "",
    "start": [
      2021,
      3,
      3,
      1,
      0
    ],
    "duration": {
      "hours": 2
    },
    "startInputType": "utc",
    "uid": "53a02cc0-3c00-46f8-8423-c5c5bef3889e"
  },
  {
    "title": "Sacramento City Council",
    "description": "Sign up to take notes for this meeting at https://www.socialjusticesac.org/wix-sac-city-council",
    "url": "",
    "start": [
      2021,
      3,
      9,
      22,
      0
    ],
    "duration": {
      "hours": 2
    },
    "startInputType": "utc",
    "uid": "e4dd4aad-6e23-40c3-9f2e-5c020cfe7bab"
  },
  {
    "title": "Sacramento City Council",
    "description": "Sign up to take notes for this meeting at https://www.socialjusticesac.org/wix-sac-city-council",
    "url": "",
    "start": [
      2021,
      3,
      16,
      21,
      0
    ],
    "duration": {
      "hours": 2
    },
    "startInputType": "utc",
    "uid": "5003abcc-be2d-4caf-9742-32125644e142"
  },
  {
    "title": "Sacramento City Council",
    "description": "Sign up to take notes for this meeting at https://www.socialjusticesac.org/wix-sac-city-council",
    "url": "",
    "start": [
      2021,
      3,
      17,
      0,
      0
    ],
    "duration": {
      "hours": 2
    },
    "startInputType": "utc",
    "uid": "b43b7daa-2609-4877-a580-f72bb032a97f"
  },
  {
    "title": "Sacramento City Council",
    "description": "Sign up to take notes for this meeting at https://www.socialjusticesac.org/wix-sac-city-council",
    "url": "",
    "start": [
      2021,
      4,
      7,
      0,
      0
    ],
    "duration": {
      "hours": 2
    },
    "startInputType": "utc",
    "uid": "37f5293a-c822-45e4-8d22-c490dd99ce35"
  },
  {
    "title": "Sacramento City Council",
    "description": "Sign up to take notes for this meeting at https://www.socialjusticesac.org/wix-sac-city-council",
    "url": "",
    "start": [
      2021,
      4,
      13,
      21,
      0
    ],
    "duration": {
      "hours": 2
    },
    "startInputType": "utc",
    "uid": "995d8e73-cae2-4a1c-a63b-1dc90bd43d75"
  },
  {
    "title": "Sacramento City Council",
    "description": "Sign up to take notes for this meeting at https://www.socialjusticesac.org/wix-sac-city-council",
    "url": "",
    "start": [
      2021,
      4,
      20,
      21,
      0
    ],
    "duration": {
      "hours": 2
    },
    "startInputType": "utc",
    "uid": "50af5141-9422-42c0-aec0-d732950d24d7"
  },
  {
    "title": "Sacramento City Council",
    "description": "Sign up to take notes for this meeting at https://www.socialjusticesac.org/wix-sac-city-council",
    "url": "",
    "start": [
      2021,
      4,
      21,
      0,
      0
    ],
    "duration": {
      "hours": 2
    },
    "startInputType": "utc",
    "uid": "c66853a7-21de-4271-a8f9-4876d2296247"
  },
  {
    "title": "Sacramento City Council",
    "description": "Sign up to take notes for this meeting at https://www.socialjusticesac.org/wix-sac-city-council",
    "url": "",
    "start": [
      2021,
      5,
      5,
      0,
      0
    ],
    "duration": {
      "hours": 2
    },
    "startInputType": "utc",
    "uid": "74bd96cc-6480-4923-a9c6-aabc803b77af"
  },
  {
    "title": "Sacramento City Council",
    "description": "Sign up to take notes for this meeting at https://www.socialjusticesac.org/wix-sac-city-council",
    "url": "",
    "start": [
      2021,
      5,
      18,
      21,
      0
    ],
    "duration": {
      "hours": 2
    },
    "startInputType": "utc",
    "uid": "97de5bc1-e91f-4542-bd7d-543f3e1c76f6"
  },
  {
    "title": "Sacramento City Council",
    "description": "Sign up to take notes for this meeting at https://www.socialjusticesac.org/wix-sac-city-council",
    "url": "",
    "start": [
      2021,
      5,
      19,
      0,
      0
    ],
    "duration": {
      "hours": 2
    },
    "startInputType": "utc",
    "uid": "cf66fe1c-f0a3-4151-9fb1-593ae51232c3"
  },
  {
    "title": "Sacramento City Council",
    "description": "Sign up to take notes for this meeting at https://www.socialjusticesac.org/wix-sac-city-council",
    "url": "",
    "start": [
      2021,
      5,
      25,
      21,
      0
    ],
    "duration": {
      "hours": 2
    },
    "startInputType": "utc",
    "uid": "17e2478a-39e3-47ed-83ac-cb5fcad1a240"
  },
  {
    "title": "Sacramento City Council",
    "description": "Sign up to take notes for this meeting at https://www.socialjusticesac.org/wix-sac-city-council",
    "url": "",
    "start": [
      2021,
      5,
      26,
      0,
      0
    ],
    "duration": {
      "hours": 2
    },
    "startInputType": "utc",
    "uid": "6329990f-56d9-4d5b-a20a-fcff81fa6db0"
  },
  {
    "title": "Sacramento City Council",
    "description": "Sign up to take notes for this meeting at https://www.socialjusticesac.org/wix-sac-city-council",
    "url": "",
    "start": [
      2021,
      6,
      2,
      0,
      0
    ],
    "duration": {
      "hours": 2
    },
    "startInputType": "utc",
    "uid": "bb874104-574b-448b-9026-4917c0cf2867"
  },
  {
    "title": "Sacramento City Council",
    "description": "Sign up to take notes for this meeting at https://www.socialjusticesac.org/wix-sac-city-council",
    "url": "",
    "start": [
      2021,
      6,
      8,
      21,
      0
    ],
    "duration": {
      "hours": 2
    },
    "startInputType": "utc",
    "uid": "f80b925b-4f63-4c53-9e6f-dc376846cc46"
  },
  {
    "title": "Sacramento City Council",
    "description": "Sign up to take notes for this meeting at https://www.socialjusticesac.org/wix-sac-city-council",
    "url": "",
    "start": [
      2021,
      6,
      15,
      21,
      0
    ],
    "duration": {
      "hours": 2
    },
    "startInputType": "utc",
    "uid": "8001b699-101e-4231-b911-d84172f07a95"
  },
  {
    "title": "Sacramento City Council",
    "description": "Sign up to take notes for this meeting at https://www.socialjusticesac.org/wix-sac-city-council",
    "url": "",
    "start": [
      2021,
      6,
      16,
      0,
      0
    ],
    "duration": {
      "hours": 2
    },
    "startInputType": "utc",
    "uid": "e37390d9-4299-4dd2-9e79-c16e689a7350"
  },
  {
    "title": "Sacramento City Council",
    "description": "Sign up to take notes for this meeting at https://www.socialjusticesac.org/wix-sac-city-council",
    "url": "",
    "start": [
      2021,
      6,
      29,
      21,
      0
    ],
    "duration": {
      "hours": 2
    },
    "startInputType": "utc",
    "uid": "ae6f4763-ca9e-4664-9acc-d6c2b73470e4"
  },
  {
    "title": "Sacramento City Council",
    "description": "Sign up to take notes for this meeting at https://www.socialjusticesac.org/wix-sac-city-council",
    "url": "",
    "start": [
      2021,
      7,
      20,
      21,
      0
    ],
    "duration": {
      "hours": 2
    },
    "startInputType": "utc",
    "uid": "b38cec6e-5a23-4c13-8475-bec7d8c97c5d"
  },
  {
    "title": "Sacramento City Council",
    "description": "Sign up to take notes for this meeting at https://www.socialjusticesac.org/wix-sac-city-council",
    "url": "",
    "start": [
      2021,
      7,
      28,
      0,
      0
    ],
    "duration": {
      "hours": 2
    },
    "startInputType": "utc",
    "uid": "3c225657-b44c-4954-82ba-98e71ca5019c"
  },
  {
    "title": "Sacramento City Council",
    "description": "Sign up to take notes for this meeting at https://www.socialjusticesac.org/wix-sac-city-council",
    "url": "",
    "start": [
      2021,
      8,
      10,
      21,
      0
    ],
    "duration": {
      "hours": 2
    },
    "startInputType": "utc",
    "uid": "9d026050-782c-4d5b-8c57-f8a900c940fc"
  },
  {
    "title": "Sacramento City Council",
    "description": "Sign up to take notes for this meeting at https://www.socialjusticesac.org/wix-sac-city-council",
    "url": "",
    "start": [
      2021,
      8,
      17,
      21,
      0
    ],
    "duration": {
      "hours": 2
    },
    "startInputType": "utc",
    "uid": "437a21d8-1f88-415d-a068-0b63591b2112"
  },
  {
    "title": "Sacramento City Council",
    "description": "Sign up to take notes for this meeting at https://www.socialjusticesac.org/wix-sac-city-council",
    "url": "",
    "start": [
      2021,
      8,
      18,
      0,
      0
    ],
    "duration": {
      "hours": 2
    },
    "startInputType": "utc",
    "uid": "45b8e3ba-10fd-4830-9a1e-445f5e18d08f"
  },
  {
    "title": "Sacramento City Council",
    "description": "Sign up to take notes for this meeting at https://www.socialjusticesac.org/wix-sac-city-council",
    "url": "",
    "start": [
      2021,
      8,
      25,
      0,
      0
    ],
    "duration": {
      "hours": 2
    },
    "startInputType": "utc",
    "uid": "68967316-8a74-4ea2-8cae-f936fbc323af"
  },
  {
    "title": "Sacramento City Council",
    "description": "Sign up to take notes for this meeting at https://www.socialjusticesac.org/wix-sac-city-council",
    "url": "",
    "start": [
      2021,
      9,
      14,
      21,
      0
    ],
    "duration": {
      "hours": 2
    },
    "startInputType": "utc",
    "uid": "995a02f8-ed81-47d7-a0ee-492050bda7b0"
  },
  {
    "title": "Sacramento City Council",
    "description": "Sign up to take notes for this meeting at https://www.socialjusticesac.org/wix-sac-city-council",
    "url": "",
    "start": [
      2021,
      9,
      21,
      21,
      0
    ],
    "duration": {
      "hours": 2
    },
    "startInputType": "utc",
    "uid": "c675b853-e631-4ca7-b060-45876f99b93f"
  },
  {
    "title": "Sacramento City Council",
    "description": "Sign up to take notes for this meeting at https://www.socialjusticesac.org/wix-sac-city-council",
    "url": "",
    "start": [
      2021,
      9,
      22,
      0,
      0
    ],
    "duration": {
      "hours": 2
    },
    "startInputType": "utc",
    "uid": "826219bb-1ea2-4629-80f0-fe73097b6c57"
  },
  {
    "title": "Sacramento City Council",
    "description": "Sign up to take notes for this meeting at https://www.socialjusticesac.org/wix-sac-city-council",
    "url": "",
    "start": [
      2021,
      10,
      12,
      21,
      0
    ],
    "duration": {
      "hours": 2
    },
    "startInputType": "utc",
    "uid": "1506f03f-0f35-4dac-8223-2ff4b18e1c36"
  },
  {
    "title": "Sacramento City Council",
    "description": "Sign up to take notes for this meeting at https://www.socialjusticesac.org/wix-sac-city-council",
    "url": "",
    "start": [
      2021,
      10,
      19,
      21,
      0
    ],
    "duration": {
      "hours": 2
    },
    "startInputType": "utc",
    "uid": "d778e3a5-3eeb-47eb-a3f5-9ddf362190f8"
  },
  {
    "title": "Sacramento City Council",
    "description": "Sign up to take notes for this meeting at https://www.socialjusticesac.org/wix-sac-city-council",
    "url": "",
    "start": [
      2021,
      10,
      20,
      0,
      0
    ],
    "duration": {
      "hours": 2
    },
    "startInputType": "utc",
    "uid": "a0cea0d8-d9a1-4344-a11e-b3a03c2edf54"
  },
  {
    "title": "Sacramento City Council",
    "description": "Sign up to take notes for this meeting at https://www.socialjusticesac.org/wix-sac-city-council",
    "url": "",
    "start": [
      2021,
      10,
      26,
      21,
      0
    ],
    "duration": {
      "hours": 2
    },
    "startInputType": "utc",
    "uid": "80796f84-f882-47d3-ac01-95bffcd1daee"
  },
  {
    "title": "Sacramento City Council",
    "description": "Sign up to take notes for this meeting at https://www.socialjusticesac.org/wix-sac-city-council",
    "url": "",
    "start": [
      2021,
      10,
      27,
      0,
      0
    ],
    "duration": {
      "hours": 2
    },
    "startInputType": "utc",
    "uid": "b480fc21-6b08-4684-8853-2cefb32dbac1"
  },
  {
    "title": "Sacramento City Council",
    "description": "Sign up to take notes for this meeting at https://www.socialjusticesac.org/wix-sac-city-council",
    "url": "",
    "start": [
      2021,
      11,
      9,
      22,
      0
    ],
    "duration": {
      "hours": 2
    },
    "startInputType": "utc",
    "uid": "a5f72ee3-780a-4487-a2de-1cc9ca69b495"
  },
  {
    "title": "Sacramento City Council",
    "description": "Sign up to take notes for this meeting at https://www.socialjusticesac.org/wix-sac-city-council",
    "url": "",
    "start": [
      2021,
      11,
      16,
      22,
      0
    ],
    "duration": {
      "hours": 2
    },
    "startInputType": "utc",
    "uid": "d97951cb-db8c-45bd-ae3a-93c3d6af5a35"
  },
  {
    "title": "Sacramento City Council",
    "description": "Sign up to take notes for this meeting at https://www.socialjusticesac.org/wix-sac-city-council",
    "url": "",
    "start": [
      2021,
      11,
      17,
      1,
      0
    ],
    "duration": {
      "hours": 2
    },
    "startInputType": "utc",
    "uid": "5b34999d-e63f-4b83-8a47-ac5163ab5ce5"
  },
  {
    "title": "Sacramento City Council",
    "description": "Sign up to take notes for this meeting at https://www.socialjusticesac.org/wix-sac-city-council",
    "url": "",
    "start": [
      2021,
      12,
      1,
      1,
      0
    ],
    "duration": {
      "hours": 2
    },
    "startInputType": "utc",
    "uid": "0cd39a7d-8c74-4c23-9ab0-f4a0d2eb52b9"
  },
  {
    "title": "Sacramento City Council",
    "description": "Sign up to take notes for this meeting at https://www.socialjusticesac.org/wix-sac-city-council",
    "url": "",
    "start": [
      2021,
      12,
      7,
      22,
      0
    ],
    "duration": {
      "hours": 2
    },
    "startInputType": "utc",
    "uid": "7111b165-96e4-4dd0-bb94-20cd7a757f67"
  },
  {
    "title": "Sacramento City Council",
    "description": "Sign up to take notes for this meeting at https://www.socialjusticesac.org/wix-sac-city-council",
    "url": "",
    "start": [
      2021,
      12,
      8,
      1,
      0
    ],
    "duration": {
      "hours": 2
    },
    "startInputType": "utc",
    "uid": "b2800d28-28bc-4922-a209-83480a7ab36e"
  },
  {
    "title": "Sacramento City Council",
    "description": "Sign up to take notes for this meeting at https://www.socialjusticesac.org/wix-sac-city-council",
    "url": "",
    "start": [
      2021,
      12,
      14,
      22,
      0
    ],
    "duration": {
      "hours": 2
    },
    "startInputType": "utc",
    "uid": "a26bff3a-d381-4851-907c-b44663081542"
  },
  {
    "title": "Sacramento City Council",
    "description": "Sign up to take notes for this meeting at https://www.socialjusticesac.org/wix-sac-city-council",
    "url": "",
    "start": [
      2023,
      2,
      22,
      1,
      0
    ],
    "duration": {
      "hours": 2
    },
    "startInputType": "utc",
    "uid": "d007dce4-8bc3-4954-90b3-6a7c25bf823b"
  },
  {
    "title": "Sacramento City Council",
    "description": "Sign up to take notes for this meeting at https://www.socialjusticesac.org/wix-sac-city-council",
    "url": "",
    "start": [
      2023,
      3,
      8,
      1,
      0
    ],
    "duration": {
      "hours": 2
    },
    "startInputType": "utc",
    "uid": "c8c62891-a5cc-4a09-b2bd-c4e7c1d6f741"
  },
  {
    "title": "Sacramento City Council",
    "description": "Sign up to take notes for this meeting at https://www.socialjusticesac.org/wix-sac-city-council",
    "url": "",
    "start": [
      2023,
      3,
      15,
      0,
      0
    ],
    "duration": {
      "hours": 2
    },
    "startInputType": "utc",
    "uid": "0aee506b-9055-4db8-be6d-b02c8297a6ec"
  },
  {
    "title": "Sacramento City Council",
    "description": "Sign up to take notes for this meeting at https://www.socialjusticesac.org/wix-sac-city-council",
    "url": "",
    "start": [
      2023,
      3,
      22,
      0,
      0
    ],
    "duration": {
      "hours": 2
    },
    "startInputType": "utc",
    "uid": "1b24718f-3b35-49a6-a4d1-49305c21b683"
  },
  {
    "title": "Sacramento City Council",
    "description": "Sign up to take notes for this meeting at https://www.socialjusticesac.org/wix-sac-city-council",
    "url": "",
    "start": [
      2023,
      3,
      29,
      0,
      0
    ],
    "duration": {
      "hours": 2
    },
    "startInputType": "utc",
    "uid": "4f64b83a-f70e-48db-9aea-0a4a73f857b6"
  },
  {
    "title": "Sacramento City Council",
    "description": "Sign up to take notes for this meeting at https://www.socialjusticesac.org/wix-sac-city-council",
    "url": "",
    "start": [
      2023,
      4,
      5,
      0,
      0
    ],
    "duration": {
      "hours": 2
    },
    "startInputType": "utc",
    "uid": "7965ed88-61d2-417e-ba2a-dff9cf7805a8"
  },
  {
    "title": "Sacramento City Council",
    "description": "Sign up to take notes for this meeting at https://www.socialjusticesac.org/wix-sac-city-council",
    "url": "",
    "start": [
      2023,
      4,
      11,
      21,
      0
    ],
    "duration": {
      "hours": 2
    },
    "startInputType": "utc",
    "uid": "90197fd4-28d1-4173-963e-891a93a69a66"
  },
  {
    "title": "Sacramento City Council",
    "description": "Sign up to take notes for this meeting at https://www.socialjusticesac.org/wix-sac-city-council",
    "url": "",
    "start": [
      2023,
      4,
      19,
      0,
      0
    ],
    "duration": {
      "hours": 2
    },
    "startInputType": "utc",
    "uid": "d34d6e56-a0f7-4665-b338-c3aa610b75e1"
  },
  {
    "title": "Sacramento City Council",
    "description": "Sign up to take notes for this meeting at https://www.socialjusticesac.org/wix-sac-city-council",
    "url": "",
    "start": [
      2023,
      5,
      3,
      0,
      0
    ],
    "duration": {
      "hours": 2
    },
    "startInputType": "utc",
    "uid": "41452e65-ca2f-421d-af3c-95e51c17748e"
  },
  {
    "title": "Sacramento City Council",
    "description": "Sign up to take notes for this meeting at https://www.socialjusticesac.org/wix-sac-city-council",
    "url": "",
    "start": [
      2023,
      5,
      10,
      0,
      0
    ],
    "duration": {
      "hours": 2
    },
    "startInputType": "utc",
    "uid": "21078cbb-eb89-4b39-a90f-4b423055d8fb"
  },
  {
    "title": "Sacramento City Council",
    "description": "Sign up to take notes for this meeting at https://www.socialjusticesac.org/wix-sac-city-council",
    "url": "",
    "start": [
      2023,
      5,
      17,
      0,
      0
    ],
    "duration": {
      "hours": 2
    },
    "startInputType": "utc",
    "uid": "d0d3b7bc-f694-45e7-93f0-d2e663a48e4e"
  },
  {
    "title": "Sacramento City Council",
    "description": "Sign up to take notes for this meeting at https://www.socialjusticesac.org/wix-sac-city-council",
    "url": "",
    "start": [
      2023,
      5,
      24,
      0,
      0
    ],
    "duration": {
      "hours": 2
    },
    "startInputType": "utc",
    "uid": "76476fdc-600c-4ab2-a2f3-97c8f7a1d049"
  },
  {
    "title": "Sacramento City Council",
    "description": "Sign up to take notes for this meeting at https://www.socialjusticesac.org/wix-sac-city-council",
    "url": "",
    "start": [
      2023,
      5,
      31,
      0,
      0
    ],
    "duration": {
      "hours": 2
    },
    "startInputType": "utc",
    "uid": "910f3987-c18e-47b9-8dce-8c9692c6f842"
  },
  {
    "title": "Sacramento City Council",
    "description": "Sign up to take notes for this meeting at https://www.socialjusticesac.org/wix-sac-city-council",
    "url": "",
    "start": [
      2023,
      6,
      14,
      0,
      0
    ],
    "duration": {
      "hours": 2
    },
    "startInputType": "utc",
    "uid": "c62957bb-ab68-4e0c-9e3b-c6493396c5ee"
  },
  {
    "title": "Sacramento City Council",
    "description": "Sign up to take notes for this meeting at https://www.socialjusticesac.org/wix-sac-city-council",
    "url": "",
    "start": [
      2023,
      6,
      21,
      0,
      0
    ],
    "duration": {
      "hours": 2
    },
    "startInputType": "utc",
    "uid": "d859f434-5366-46ab-899b-8450b12d5dbe"
  },
  {
    "title": "Sacramento City Council",
    "description": "Sign up to take notes for this meeting at https://www.socialjusticesac.org/wix-sac-city-council",
    "url": "",
    "start": [
      2023,
      6,
      28,
      0,
      0
    ],
    "duration": {
      "hours": 2
    },
    "startInputType": "utc",
    "uid": "6976c2e8-5044-4863-bb09-13edccea421c"
  },
  {
    "title": "Sacramento City Council",
    "description": "Sign up to take notes for this meeting at https://www.socialjusticesac.org/wix-sac-city-council",
    "url": "",
    "start": [
      2023,
      7,
      26,
      0,
      0
    ],
    "duration": {
      "hours": 2
    },
    "startInputType": "utc",
    "uid": "a1faed64-9e10-48e4-9b68-a82a3619c697"
  },
  {
    "title": "Sacramento City Council",
    "description": "Sign up to take notes for this meeting at https://www.socialjusticesac.org/wix-sac-city-council",
    "url": "",
    "start": [
      2023,
      8,
      9,
      0,
      0
    ],
    "duration": {
      "hours": 2
    },
    "startInputType": "utc",
    "uid": "79e42446-7ee4-4d20-a844-177f00309538"
  },
  {
    "title": "Sacramento City Council",
    "description": "Sign up to take notes for this meeting at https://www.socialjusticesac.org/wix-sac-city-council",
    "url": "",
    "start": [
      2023,
      8,
      16,
      0,
      0
    ],
    "duration": {
      "hours": 2
    },
    "startInputType": "utc",
    "uid": "3fed8223-74a4-4569-9151-d1323323f16a"
  },
  {
    "title": "Sacramento City Council",
    "description": "Sign up to take notes for this meeting at https://www.socialjusticesac.org/wix-sac-city-council",
    "url": "",
    "start": [
      2023,
      8,
      23,
      0,
      0
    ],
    "duration": {
      "hours": 2
    },
    "startInputType": "utc",
    "uid": "d4d61fdd-eb98-4a05-9c3b-34ef7297636d"
  },
  {
    "title": "Sacramento City Council",
    "description": "Sign up to take notes for this meeting at https://www.socialjusticesac.org/wix-sac-city-council",
    "url": "",
    "start": [
      2023,
      8,
      30,
      0,
      0
    ],
    "duration": {
      "hours": 2
    },
    "startInputType": "utc",
    "uid": "7f745535-dd49-447c-83c6-e513e520824d"
  },
  {
    "title": "Sacramento City Council",
    "description": "Sign up to take notes for this meeting at https://www.socialjusticesac.org/wix-sac-city-council",
    "url": "",
    "start": [
      2023,
      9,
      6,
      0,
      0
    ],
    "duration": {
      "hours": 2
    },
    "startInputType": "utc",
    "uid": "1a32823e-d654-4133-ac1b-5d880adc3b9a"
  },
  {
    "title": "Sacramento City Council",
    "description": "Sign up to take notes for this meeting at https://www.socialjusticesac.org/wix-sac-city-council",
    "url": "",
    "start": [
      2023,
      9,
      13,
      0,
      0
    ],
    "duration": {
      "hours": 2
    },
    "startInputType": "utc",
    "uid": "cc6096b4-e325-4571-88af-c1167f6fcda0"
  },
  {
    "title": "Sacramento City Council",
    "description": "Sign up to take notes for this meeting at https://www.socialjusticesac.org/wix-sac-city-council",
    "url": "",
    "start": [
      2023,
      9,
      20,
      0,
      0
    ],
    "duration": {
      "hours": 2
    },
    "startInputType": "utc",
    "uid": "68c39301-e252-4ba9-83db-4a5851607739"
  },
  {
    "title": "Sacramento City Council",
    "description": "Sign up to take notes for this meeting at https://www.socialjusticesac.org/wix-sac-city-council",
    "url": "",
    "start": [
      2023,
      9,
      27,
      0,
      0
    ],
    "duration": {
      "hours": 2
    },
    "startInputType": "utc",
    "uid": "e06e0d26-8b40-406a-9d1f-a8503ec5e46c"
  },
  {
    "title": "Sacramento City Council",
    "description": "Sign up to take notes for this meeting at https://www.socialjusticesac.org/wix-sac-city-council",
    "url": "",
    "start": [
      2023,
      10,
      4,
      0,
      0
    ],
    "duration": {
      "hours": 2
    },
    "startInputType": "utc",
    "uid": "1755c604-9d80-49d8-8ee7-5174abfc7f66"
  },
  {
    "title": "Sacramento City Council",
    "description": "Sign up to take notes for this meeting at https://www.socialjusticesac.org/wix-sac-city-council",
    "url": "",
    "start": [
      2023,
      10,
      11,
      0,
      0
    ],
    "duration": {
      "hours": 2
    },
    "startInputType": "utc",
    "uid": "fb2c1adc-b7f6-488f-91e0-f8dbf3d899d9"
  },
  {
    "title": "Sacramento City Council",
    "description": "Sign up to take notes for this meeting at https://www.socialjusticesac.org/wix-sac-city-council",
    "url": "",
    "start": [
      2023,
      10,
      18,
      0,
      0
    ],
    "duration": {
      "hours": 2
    },
    "startInputType": "utc",
    "uid": "ea689f7a-4ce0-4cf3-bbb9-29e11c08bdd1"
  },
  {
    "title": "Sacramento City Council",
    "description": "Sign up to take notes for this meeting at https://www.socialjusticesac.org/wix-sac-city-council",
    "url": "",
    "start": [
      2023,
      10,
      25,
      0,
      0
    ],
    "duration": {
      "hours": 2
    },
    "startInputType": "utc",
    "uid": "8f151f64-3ba1-4e6d-84b3-7dfa201137e0"
  },
  {
    "title": "Sacramento City Council",
    "description": "Sign up to take notes for this meeting at https://www.socialjusticesac.org/wix-sac-city-council",
    "url": "",
    "start": [
      2023,
      11,
      1,
      0,
      0
    ],
    "duration": {
      "hours": 2
    },
    "startInputType": "utc",
    "uid": "1238a2db-4c4b-43a4-96c4-59031c760edd"
  },
  {
    "title": "Sacramento City Council",
    "description": "Sign up to take notes for this meeting at https://www.socialjusticesac.org/wix-sac-city-council",
    "url": "",
    "start": [
      2023,
      11,
      15,
      1,
      0
    ],
    "duration": {
      "hours": 2
    },
    "startInputType": "utc",
    "uid": "df4102e7-dcd3-4754-a93a-dc835a91d5bd"
  },
  {
    "title": "Sacramento City Council",
    "description": "Sign up to take notes for this meeting at https://www.socialjusticesac.org/wix-sac-city-council",
    "url": "",
    "start": [
      2023,
      11,
      29,
      1,
      0
    ],
    "duration": {
      "hours": 2
    },
    "startInputType": "utc",
    "uid": "abb5968c-ebac-4b5e-ac9f-07617eb4a08e"
  },
  {
    "title": "Sacramento City Council",
    "description": "Sign up to take notes for this meeting at https://www.socialjusticesac.org/wix-sac-city-council",
    "url": "",
    "start": [
      2023,
      12,
      6,
      1,
      0
    ],
    "duration": {
      "hours": 2
    },
    "startInputType": "utc",
    "uid": "a7a17d74-1b6c-4a43-82a3-f7818a90f6c3"
  },
  {
    "title": "Sacramento City Council",
    "description": "Sign up to take notes for this meeting at https://www.socialjusticesac.org/wix-sac-city-council",
    "url": "",
    "start": [
      2023,
      12,
      13,
      1,
      0
    ],
    "duration": {
      "hours": 2
    },
    "startInputType": "utc",
    "uid": "b3a86d04-7a44-4084-bf25-a951e05be588"
  }
]